.coveragerc
.editorconfig
.gitattributes
.gitignore
.travis.yml
CHANGES.rst
CONTRIBUTORS.rst
MANIFEST.in
README.rst
buildout.cfg
requirements.txt
setup.cfg
setup.py
travis.cfg
docs/LICENSE.GPL
docs/LICENSE.rst
docs/index.rst
src/quaive/__init__.py
src/quaive.app.taxonomy.egg-info/PKG-INFO
src/quaive.app.taxonomy.egg-info/SOURCES.txt
src/quaive.app.taxonomy.egg-info/dependency_links.txt
src/quaive.app.taxonomy.egg-info/entry_points.txt
src/quaive.app.taxonomy.egg-info/namespace_packages.txt
src/quaive.app.taxonomy.egg-info/not-zip-safe
src/quaive.app.taxonomy.egg-info/requires.txt
src/quaive.app.taxonomy.egg-info/top_level.txt
src/quaive/app/__init__.py
src/quaive/app/taxonomy/__init__.py
src/quaive/app/taxonomy/configure.zcml
src/quaive/app/taxonomy/interfaces.py
src/quaive/app/taxonomy/setuphandlers.py
src/quaive/app/taxonomy/synci18n.sh
src/quaive/app/taxonomy/testing.py
src/quaive/app/taxonomy/browser/__init__.py
src/quaive/app/taxonomy/browser/configure.zcml
src/quaive/app/taxonomy/browser/document_browser.py
src/quaive/app/taxonomy/browser/overrides/.gitkeep
src/quaive/app/taxonomy/browser/static/.gitkeep
src/quaive/app/taxonomy/browser/templates/app-document-browser.pt
src/quaive/app/taxonomy/locales/quaive.app.taxonomy.pot
src/quaive/app/taxonomy/locales/update.sh
src/quaive/app/taxonomy/profiles/default/browserlayer.xml
src/quaive/app/taxonomy/profiles/default/metadata.xml
src/quaive/app/taxonomy/profiles/testing/catalog.xml
src/quaive/app/taxonomy/profiles/testing/metadata.xml
src/quaive/app/taxonomy/profiles/testing/registry.xml
src/quaive/app/taxonomy/profiles/uninstall/browserlayer.xml
src/quaive/app/taxonomy/tests/__init__.py
src/quaive/app/taxonomy/tests/configure.zcml
src/quaive/app/taxonomy/tests/test_robot.py
src/quaive/app/taxonomy/tests/test_setup.py
src/quaive/app/taxonomy/tests/test_views.py
src/quaive/app/taxonomy/tests/robot/test_example.robot
src/quaive/app/taxonomy/tests/vocabularies/vocab.vdex
src/quaive/app/taxonomy/vocabularies/taxonomy.vdex