Metadata-Version: 1.1
Name: quaive.app.taxonomy
Version: 1.2.2
Summary: A taxonomy browser app for quaive
Home-page: https://pypi.python.org/pypi/quaive.app.taxonomy
Author: Alexander Pilz
Author-email: pilz@syslab.com
License: GPL version 2
Keywords: Python Plone
Platform: UNKNOWN
Classifier: Environment :: Web Environment
Classifier: Framework :: Plone
Classifier: Framework :: Plone :: 5.0
Classifier: Programming Language :: Python
Classifier: Programming Language :: Python :: 2.7
Classifier: Operating System :: OS Independent
Classifier: License :: OSI Approved :: GNU General Public License v2 (GPLv2)
